autonomi_client-0.6.4.dist-info/METADATA
autonomi_client-0.6.4.dist-info/WHEEL
autonomi_client/__init__.py
autonomi_client/autonomi_client.abi3.so
autonomi_client-0.6.4.dist-info/RECORD
