Metadata-Version: 2.4
Name: autonomi-client
Version: 0.6.4
Classifier: Development Status :: 4 - Beta
Classifier: Intended Audience :: Developers
Classifier: License :: OSI Approved :: GNU General Public License v3 (GPLv3)
Classifier: Programming Language :: Python :: 3
Classifier: Programming Language :: Python :: 3.8
Classifier: Programming Language :: Python :: 3.9
Classifier: Programming Language :: Python :: 3.10
Classifier: Programming Language :: Python :: 3.11
Classifier: Programming Language :: Python :: 3.12
Classifier: Programming Language :: Rust
Classifier: Programming Language :: Python :: Implementation :: CPython
Requires-Dist: maturin>=1.7.4
Requires-Dist: pip>=24.0
Requires-Dist: pytest>=8.3.4
Summary: Autonomi client API
Home-Page: https://maidsafe.net
Author-email: MaidSafe Developers <dev@maidsafe.net>
License: GPL-3.0
Requires-Python: >=3.8
Project-URL: Homepage, https://maidsafe.net
Project-URL: Repository, https://github.com/maidsafe/autonomi
